LICENSE
README.md
pyproject.toml
setup.cfg
setup.py
examples/example_autocorrelograms.py
examples/example_average_waveforms.py
examples/example_box_layout.py
examples/example_confusion_matrix.py
examples/example_cross_correlograms.py
examples/example_image.py
examples/example_markdown.py
examples/example_mountain_layout.py
examples/example_plotly.py
examples/example_position_plot.py
examples/example_raster_plot.py
examples/example_sorting_curation.py
examples/example_spike_amplitudes.py
examples/example_spike_locations.py
examples/example_splitter_layout.py
examples/example_tab_layout.py
examples/example_tiled_image.py
examples/example_timeseries_graph.py
examples/example_track_position_animation.py
examples/example_unit_locations.py
examples/example_unit_metrics_graph.py
examples/example_unit_similarity_matrix.py
examples/example_units_table.py
examples/helpers/compute_correlogram_data.py
examples/helpers/create_units_table.py
gui/node_modules/flatted/python/flatted.py
gui/node_modules/flatted/python/test.py
sortingview/__init__.py
sortingview/sortingview_view_url.py
sortingview/version.py
sortingview.egg-info/PKG-INFO
sortingview.egg-info/SOURCES.txt
sortingview.egg-info/dependency_links.txt
sortingview.egg-info/requires.txt
sortingview.egg-info/top_level.txt
sortingview/SpikeSortingView/Figure.py
sortingview/SpikeSortingView/MultiTimeseries.py
sortingview/SpikeSortingView/SpikeSortingView.py
sortingview/SpikeSortingView/__init__.py
sortingview/SpikeSortingView/_autocorrelograms_view.py
sortingview/SpikeSortingView/_average_waveforms_view.py
sortingview/SpikeSortingView/_create_autocorrelograms.py
sortingview/SpikeSortingView/_create_average_waveforms.py
sortingview/SpikeSortingView/_create_electrode_geometry.py
sortingview/SpikeSortingView/_create_live_cross_correlograms.py
sortingview/SpikeSortingView/_create_mountain_layout.py
sortingview/SpikeSortingView/_create_raster_plot.py
sortingview/SpikeSortingView/_create_spike_amplitudes.py
sortingview/SpikeSortingView/_create_summary.py
sortingview/SpikeSortingView/_create_units_table.py
sortingview/SpikeSortingView/_cross_correlograms_view.py
